tpi/__init__.py
tpi/__main__.py
tpi/_dist_ver.py
tpi/bin.py
tpi/main.py
tpi/terraform.py
tpi/templates/main.tf
tpi-2.1.0.dist-info/LICENCE
tpi-2.1.0.dist-info/METADATA
tpi-2.1.0.dist-info/WHEEL
tpi-2.1.0.dist-info/entry_points.txt
tpi-2.1.0.dist-info/top_level.txt
tpi-2.1.0.dist-info/RECORD
