Metadata-Version: 2.1
Name: tpi
Version: 2.1.0
Summary: Terraform Provider Iterative
Home-page: https://github.com/iterative/tpi
Author: Casper da Costa-Luis
Author-email: casper.dcl@physics.org
Maintainer: Iterative
Maintainer-email: support@cml.dev
License: Apache-2.0
Project-URL: Changelog, https://github.com/iterative/tpi/releases
Project-URL: Documentation, https://github.com/iterative/tpi/#tpi
Keywords: terraform,cloud,orchestration
Platform: any
Classifier: Development Status :: 3 - Alpha
Classifier: Environment :: Console
Classifier: Environment :: MacOS X
Classifier: Environment :: Other Environment
Classifier: Environment :: Plugins
Classifier: Environment :: Win32 (MS Windows)
Classifier: Intended Audience :: Developers
Classifier: Intended Audience :: Education
Classifier: Intended Audience :: End Users/Desktop
Classifier: Intended Audience :: Other Audience
Classifier: Intended Audience :: System Administrators
Classifier: License :: OSI Approved :: Apache Software License
Classifier: Operating System :: MacOS
Classifier: Operating System :: Microsoft :: Windows
Classifier: Operating System :: POSIX
Classifier: Operating System :: Unix
Classifier: Programming Language :: Other Scripting Engines
Classifier: Programming Language :: Python
Classifier: Programming Language :: Python :: 3
Classifier: Programming Language :: Python :: 3 :: Only
Classifier: Programming Language :: Python :: 3.4
Classifier: Programming Language :: Python :: 3.5
Classifier: Programming Language :: Python :: 3.6
Classifier: Programming Language :: Python :: 3.7
Classifier: Programming Language :: Python :: 3.8
Classifier: Programming Language :: Python :: 3.9
Classifier: Topic :: Desktop Environment
Classifier: Topic :: Education :: Computer Aided Instruction (CAI)
Classifier: Topic :: Education :: Testing
Classifier: Topic :: Internet
Classifier: Topic :: Other/Nonlisted Topic
Classifier: Topic :: Scientific/Engineering
Classifier: Topic :: Software Development
Classifier: Topic :: Software Development :: Build Tools
Classifier: Topic :: Software Development :: Libraries
Classifier: Topic :: Software Development :: Libraries :: Python Modules
Classifier: Topic :: Software Development :: Pre-processors
Classifier: Topic :: Software Development :: User Interfaces
Classifier: Topic :: System
Classifier: Topic :: System :: Distributed Computing
Classifier: Topic :: System :: Installation/Setup
Classifier: Topic :: System :: Systems Administration
Classifier: Topic :: Utilities
Provides: tpi
Requires-Python: >=3.4
License-File: LICENCE
Requires-Dist: funcy
Requires-Dist: jinja2 (>=2.0.0)
Requires-Dist: miutil[web] (>=0.7.0)
Requires-Dist: python-terraform (>=0.10.1)
Requires-Dist: setuptools
Provides-Extra: ssh
Requires-Dist: asyncssh ; extra == 'ssh'
